{
  "$schema": "https://typedoc.org/schema.json",
  "entryPoints": ["./src/index.ts"],
  "exclude": ["**/*.test.ts"],
  "out": "docs",
  "versions": {},
  "pluginPages": {
    "source": "get-started",
    "pages": [
      {
        "title": "Get Started",
        "children": [
          { "title": "Lexer", "source": "lexer.md" },
          {
            "title": "ELR Parser",
            "source": "ELR-parser.md",
            "children": [
              {
                "title": "Expectation & Re-Lex",
                "source": "expectation-re-lex.md"
              },
              {
                "title": "Advanced Parser",
                "source": "advanced-parser.md"
              }
            ]
          }
        ]
      }
    ]
  }
}
